manim_automata/.DS_Store
manim_automata/__init__.py
manim_automata/mobjects/__init__.py
manim_automata/mobjects/automata_dependencies/automata.py
manim_automata/mobjects/automata_dependencies/state.py
manim_automata/mobjects/automata_dependencies/transitition.py
manim_automata/mobjects/automata_dependencies/xml_parser.py
manim_automata/mobjects/manim_animations.py
manim_automata/mobjects/manim_automaton.py
manim_automata/mobjects/manim_automaton_input.py
manim_automata/mobjects/manim_cli.py
manim_automata/mobjects/manim_determinstic_finite_state_automaton.py
manim_automata/mobjects/manim_non_determinstic_finite_state_automaton.py
manim_automata/mobjects/manim_pushdown_automaton.py
manim_automata/mobjects/manim_state.py
manim_automata/mobjects/manim_transition.py
manim_automata/mobjects/manim_turing_machine.py
manim_automata-0.2.14.dist-info/entry_points.txt
manim_automata-0.2.14.dist-info/LICENSE.txt
manim_automata-0.2.14.dist-info/METADATA
manim_automata-0.2.14.dist-info/WHEEL
manim_automata-0.2.14.dist-info/RECORD
