Metadata-Version: 2.1
Name: manim-automata
Version: 0.2.14
Summary: A Manim implementation of automata
Home-page: https://github.com/SeanNelsonIO/manim-automata
License: MIT
Author: Sean Nelson
Author-email: snelson01010@gmail.com
Requires-Python: >=3.9,<4.0
Classifier: License :: OSI Approved :: MIT License
Classifier: Programming Language :: Python :: 3
Classifier: Programming Language :: Python :: 3.9
Classifier: Programming Language :: Python :: 3.10
Classifier: Programming Language :: Python :: 3.11
Requires-Dist: xmltodict (>=0.13.0,<0.14.0)
Project-URL: Repository, https://github.com/SeanNelsonIO/manim-automata
